pyurlx/__init__.py
pyurlx/tools.py
pyurlx-4.0.0.dist-info/LICENSE
pyurlx-4.0.0.dist-info/METADATA
pyurlx-4.0.0.dist-info/WHEEL
pyurlx-4.0.0.dist-info/top_level.txt
pyurlx-4.0.0.dist-info/RECORD
