Metadata-Version: 2.1
Name: pyurlx
Version: 4.0.0
Summary: A cool python module which can do link management using the URLx API
Author-email: James Marke <mikeoxlong@saintly.com>, Callum Cardy <pythonscratcher@email.cz>
License: BSD-3-Clause
Keywords: url,shorten,link
Classifier: Programming Language :: Python :: 2.7
Requires-Python: >=2.7
License-File: LICENSE
Requires-Dist: requests
Requires-Dist: importlib-metadata ; python_version < "2.7"
